openensembles/__init__.py
openensembles/clustering_algorithms.py
openensembles/cooccurrence.py
openensembles/finishing.py
openensembles/init_old.py
openensembles/mutualinformation.py
openensembles/openensembles.py
openensembles/transforms.py
openensembles/validation.py
OpenEnsembles-2.0.0.dist-info/LICENSE
OpenEnsembles-2.0.0.dist-info/METADATA
OpenEnsembles-2.0.0.dist-info/WHEEL
OpenEnsembles-2.0.0.dist-info/top_level.txt
OpenEnsembles-2.0.0.dist-info/RECORD
